pawlogger/__init__.py
pawlogger/config.py
pawlogger/config_loguru.py
pawlogger/consts.py
pawlogger/loggingdecorators/__init__.py
pawlogger/loggingdecorators/consts_formats.py
pawlogger/loggingdecorators/decorators.py
pawlogger/loggingdecorators/legacy.py
pawlogger/tests/loggingdecorators/conftest.py
pawlogger/tests/loggingdecorators/test_on_call.py
pawlogger/tests/loggingdecorators/test_on_class.py
pawlogger/tests/loggingdecorators/test_on_init.py
pawlogger/tests/loggingdecorators/test_on_new.py
pawlogger/tests/pawlogger/test_l_config.py
pawlogger-0.1.0.dist-info/WHEEL
pawlogger-0.1.0.dist-info/METADATA
pawlogger-0.1.0.dist-info/RECORD
